my_simple_tree_library-0.2.dist-info/DESCRIPTION.rst
my_simple_tree_library-0.2.dist-info/METADATA
my_simple_tree_library-0.2.dist-info/RECORD
my_simple_tree_library-0.2.dist-info/WHEEL
my_simple_tree_library-0.2.dist-info/entry_points.txt
my_simple_tree_library-0.2.dist-info/metadata.json
my_simple_tree_library-0.2.dist-info/top_level.txt
streelib/__init__.py
streelib/algths.py
streelib/halperfuncs.py
streelib/structures.py
